nuvepro_runner/__init__.py
nuvepro_runner/fs.py
nuvepro_runner/process.py
nuvepro_runner/runner.py
nuvepro_runner/sandbox.py
nuvepro_runner/sdk.py
nuvepro_runner-0.1.6.dist-info/licenses/LICENSE .txt
nuvepro_runner-0.1.6.dist-info/METADATA
nuvepro_runner-0.1.6.dist-info/WHEEL
nuvepro_runner-0.1.6.dist-info/top_level.txt
nuvepro_runner-0.1.6.dist-info/RECORD
