Metadata-Version: 2.4
Name: nuvepro-runner
Version: 0.1.6
Summary: A lightweight runner framework for sandboxed environments
Author-email: Rishabh Mishra <rishabh@nuvepro.com>
License: MIT
Project-URL: Homepage, https://github.com/rishah/nuvepro_runner
Classifier: Programming Language :: Python :: 3
Classifier: License :: OSI Approved :: MIT License
Classifier: Operating System :: OS Independent
Requires-Python: >=3.8
License-File: LICENSE .txt
Requires-Dist: requests>=2.25.1
Requires-Dist: httpx>=0.23.0
Dynamic: license-file
